database_automation/__init__.py
database_automation/mongo_crud.py
MongoConnectTestfinal-0.0.2.dist-info/METADATA
MongoConnectTestfinal-0.0.2.dist-info/WHEEL
MongoConnectTestfinal-0.0.2.dist-info/top_level.txt
MongoConnectTestfinal-0.0.2.dist-info/RECORD
